README.txt
setup.py
deps/__init__.py
deps/models.py
deps/management/__init__.py
deps/management/commands/__init__.py
deps/management/commands/up.py
django_dependency.egg-info/PKG-INFO
django_dependency.egg-info/SOURCES.txt
django_dependency.egg-info/dependency_links.txt
django_dependency.egg-info/requires.txt
django_dependency.egg-info/top_level.txt
scripts/create_deps.py