Metadata-Version: 1.0
Name: django-dependency
Version: 1.1
Summary: Django app to help manage external dependencies
Home-page: http://code.google.com/p/django-dependency/
Author: Caktus Consulting Group
Author-email: solutions@caktusgroup.com
License: LICENSE.txt
Platform: UNKNOWN
